gravlax/__init__.py
gravlax/context.py
gravlax/tree_utils.py
gravlax/types.py
gravlax/write_csv.py
gravlax-0.0.1.dist-info/METADATA
gravlax-0.0.1.dist-info/WHEEL
gravlax-0.0.1.dist-info/licenses/LICENSE
gravlax-0.0.1.dist-info/RECORD
