Metadata-Version: 2.1
Name: gravlax
Version: 0.0.1
Summary: Basic training utils for JAX.
Project-URL: repository, https://github.com/magrilab/gravlax
Author-email: Daniel Kelshaw <djk21@ic.ac.uk>
License: MIT License
License-File: LICENSE
Requires-Python: >=3.10
Requires-Dist: hatch
Requires-Dist: jax
Requires-Dist: jaxlib
Provides-Extra: dev
Requires-Dist: mkdocs; extra == 'dev'
Requires-Dist: mkdocs-material; extra == 'dev'
Requires-Dist: mkdocstrings-python; extra == 'dev'
Requires-Dist: pip-tools; extra == 'dev'
Requires-Dist: pre-commit; extra == 'dev'
Requires-Dist: pyright; extra == 'dev'
Requires-Dist: pytest; extra == 'dev'
Requires-Dist: ruff; extra == 'dev'
Provides-Extra: jupyter
Requires-Dist: ipykernel; extra == 'jupyter'
Requires-Dist: jupyterlab; extra == 'jupyter'
